markov_groove/__init__.py
markov_groove/audio_file.py
markov_groove/onset_detector.py
markov_groove/sampler.py
markov_groove/sequencer/__init__.py
markov_groove/sequencer/audio_sequencer.py
markov_groove/sequencer/midi_sequencer.py
markov_groove/sequencer/sequencer.py
markov_groove/util.py
markov_groove-0.1.0.dist-info/WHEEL
markov_groove-0.1.0.dist-info/METADATA
markov_groove-0.1.0.dist-info/RECORD
