Metadata-Version: 2.1
Name: markov-groove
Version: 0.1.0
Summary: Generate drum loops by using hidden markov chains.
License: AGPL-3.0-or-later
Author: Jan-Niclas de Vries
Author-email: jan_dev@uni-bremen.de
Requires-Python: >=3.8,<4.0
Classifier: License :: OSI Approved :: GNU Affero General Public License v3 or later (AGPLv3+)
Classifier: Programming Language :: Python :: 3
Classifier: Programming Language :: Python :: 3.8
Classifier: Programming Language :: Python :: 3.9
Requires-Dist: click (>=7.1.1,<8.0.0)
Requires-Dist: essentia (>=2.1b5,<3.0)
Requires-Dist: matplotlib (>=3.1.3,<4.0.0)
Requires-Dist: more-itertools (>=8.2.0,<9.0.0)
Requires-Dist: nptyping (>=1.3.0,<2.0.0)
Requires-Dist: numpy (==1.18.2)
Requires-Dist: pomegranate (>=0.13.4,<0.14.0)
Requires-Dist: pretty_midi (>=0.2.9,<0.3.0)
Requires-Dist: pyfluidsynth (>=1.2.5,<2.0.0)
